[
 {
  "description": null,
  "docstatus": 0,
  "doctype": "Item Group",
  "filter_attributes": [],
  "filter_fields": [],
  "image": null,
  "include_descendants": 0,
  "is_group": 0,
  "item_group_defaults": [],
  "item_group_name": "Products",
  "modified": "2024-07-26 11:08:28.266232",
  "name": "Products",
  "old_parent": "All Item Groups",
  "parent_item_group": "All Item Groups",
  "route": "products",
  "show_in_website": 0,
  "slideshow": null,
  "taxes": [],
  "website_specifications": [],
  "website_title": null,
  "weightage": 0
 },
 {
  "description": null,
  "docstatus": 0,
  "doctype": "Item Group",
  "filter_attributes": [],
  "filter_fields": [],
  "image": null,
  "include_descendants": 0,
  "is_group": 0,
  "item_group_defaults": [],
  "item_group_name": "Raw Material",
  "modified": "2024-07-26 11:08:28.284641",
  "name": "Raw Material",
  "old_parent": "All Item Groups",
  "parent_item_group": "All Item Groups",
  "route": "raw-material",
  "show_in_website": 0,
  "slideshow": null,
  "taxes": [],
  "website_specifications": [],
  "website_title": null,
  "weightage": 0
 },
 {
  "description": null,
  "docstatus": 0,
  "doctype": "Item Group",
  "filter_attributes": [],
  "filter_fields": [],
  "image": null,
  "include_descendants": 0,
  "is_group": 0,
  "item_group_defaults": [],
  "item_group_name": "Services",
  "modified": "2024-07-26 11:08:28.295921",
  "name": "Services",
  "old_parent": "All Item Groups",
  "parent_item_group": "All Item Groups",
  "route": "services",
  "show_in_website": 0,
  "slideshow": null,
  "taxes": [],
  "website_specifications": [],
  "website_title": null,
  "weightage": 0
 },
 {
  "description": null,
  "docstatus": 0,
  "doctype": "Item Group",
  "filter_attributes": [],
  "filter_fields": [],
  "image": null,
  "include_descendants": 0,
  "is_group": 0,
  "item_group_defaults": [],
  "item_group_name": "Sub Assemblies",
  "modified": "2024-07-26 11:08:28.313835",
  "name": "Sub Assemblies",
  "old_parent": "All Item Groups",
  "parent_item_group": "All Item Groups",
  "route": "sub-assemblies",
  "show_in_website": 0,
  "slideshow": null,
  "taxes": [],
  "website_specifications": [],
  "website_title": null,
  "weightage": 0
 },
 {
  "description": null,
  "docstatus": 0,
  "doctype": "Item Group",
  "filter_attributes": [],
  "filter_fields": [],
  "image": null,
  "include_descendants": 0,
  "is_group": 0,
  "item_group_defaults": [],
  "item_group_name": "Consumable",
  "modified": "2024-07-26 11:08:28.327940",
  "name": "Consumable",
  "old_parent": "All Item Groups",
  "parent_item_group": "All Item Groups",
  "route": "consumable",
  "show_in_website": 0,
  "slideshow": null,
  "taxes": [],
  "website_specifications": [],
  "website_title": null,
  "weightage": 0
 },
 {
  "description": null,
  "docstatus": 0,
  "doctype": "Item Group",
  "filter_attributes": [],
  "filter_fields": [],
  "image": "/files/weeders-1.jpg",
  "include_descendants": 0,
  "is_group": 0,
  "item_group_defaults": [
   {
    "buying_cost_center": null,
    "company": "nature farmeasy",
    "default_discount_account": null,
    "default_price_list": "Standard Selling",
    "default_provisional_account": null,
    "default_supplier": null,
    "default_warehouse": "Stores - NF",
    "deferred_expense_account": null,
    "deferred_revenue_account": null,
    "expense_account": null,
    "income_account": null,
    "parent": "Weeder",
    "parentfield": "item_group_defaults",
    "parenttype": "Item Group",
    "selling_cost_center": null
   }
  ],
  "item_group_name": "Weeder",
  "modified": "2024-07-31 20:20:18.892810",
  "name": "Weeder",
  "old_parent": "All Item Groups",
  "parent_item_group": "All Item Groups",
  "route": "weeder",
  "show_in_website": 1,
  "slideshow": null,
  "taxes": [],
  "website_specifications": [],
  "website_title": null,
  "weightage": 0
 },
 {
  "description": null,
  "docstatus": 0,
  "doctype": "Item Group",
  "filter_attributes": [],
  "filter_fields": [],
  "image": "/files/Processing-Equipment-2.jpg",
  "include_descendants": 0,
  "is_group": 0,
  "item_group_defaults": [
   {
    "buying_cost_center": null,
    "company": "nature farmeasy",
    "default_discount_account": null,
    "default_price_list": "Standard Selling",
    "default_provisional_account": null,
    "default_supplier": null,
    "default_warehouse": "Stores - NF",
    "deferred_expense_account": null,
    "deferred_revenue_account": null,
    "expense_account": null,
    "income_account": null,
    "parent": "Mixers",
    "parentfield": "item_group_defaults",
    "parenttype": "Item Group",
    "selling_cost_center": null
   }
  ],
  "item_group_name": "Mixers",
  "modified": "2024-08-01 18:04:17.092040",
  "name": "Mixers",
  "old_parent": "All Item Groups",
  "parent_item_group": "All Item Groups",
  "route": "mixers",
  "show_in_website": 1,
  "slideshow": null,
  "taxes": [],
  "website_specifications": [],
  "website_title": null,
  "weightage": 0
 },
 {
  "description": null,
  "docstatus": 0,
  "doctype": "Item Group",
  "filter_attributes": [],
  "filter_fields": [],
  "image": "/files/controller unit single tank.png",
  "include_descendants": 0,
  "is_group": 0,
  "item_group_defaults": [
   {
    "buying_cost_center": null,
    "company": "nature farmeasy",
    "default_discount_account": null,
    "default_price_list": "Standard Selling",
    "default_provisional_account": null,
    "default_supplier": null,
    "default_warehouse": "Stores - NF",
    "deferred_expense_account": null,
    "deferred_revenue_account": null,
    "expense_account": null,
    "income_account": null,
    "parent": "DJ Units",
    "parentfield": "item_group_defaults",
    "parenttype": "Item Group",
    "selling_cost_center": null
   }
  ],
  "item_group_name": "DJ Units",
  "modified": "2024-08-01 18:02:54.495662",
  "name": "DJ Units",
  "old_parent": "All Item Groups",
  "parent_item_group": "All Item Groups",
  "route": "dj-units",
  "show_in_website": 1,
  "slideshow": null,
  "taxes": [],
  "website_specifications": [],
  "website_title": null,
  "weightage": 0
 },
 {
  "description": null,
  "docstatus": 0,
  "doctype": "Item Group",
  "filter_attributes": [],
  "filter_fields": [],
  "image": "/files/cartimage.png",
  "include_descendants": 0,
  "is_group": 0,
  "item_group_defaults": [
   {
    "buying_cost_center": null,
    "company": "nature farmeasy",
    "default_discount_account": null,
    "default_price_list": "Standard Selling",
    "default_provisional_account": null,
    "default_supplier": null,
    "default_warehouse": "Stores - NF",
    "deferred_expense_account": null,
    "deferred_revenue_account": null,
    "expense_account": null,
    "income_account": null,
    "parent": "Weighing cart",
    "parentfield": "item_group_defaults",
    "parenttype": "Item Group",
    "selling_cost_center": null
   }
  ],
  "item_group_name": "Weighing cart",
  "modified": "2024-08-01 18:04:36.840587",
  "name": "Weighing cart",
  "old_parent": "All Item Groups",
  "parent_item_group": "All Item Groups",
  "route": "weighing-cart",
  "show_in_website": 1,
  "slideshow": null,
  "taxes": [],
  "website_specifications": [],
  "website_title": null,
  "weightage": 0
 },
 {
  "description": null,
  "docstatus": 0,
  "doctype": "Item Group",
  "filter_attributes": [],
  "filter_fields": [],
  "image": "/files/double pump agriculture sprayer.png",
  "include_descendants": 0,
  "is_group": 0,
  "item_group_defaults": [
   {
    "buying_cost_center": null,
    "company": "nature farmeasy",
    "default_discount_account": null,
    "default_price_list": "Standard Selling",
    "default_provisional_account": null,
    "default_supplier": null,
    "default_warehouse": "Stores - NF",
    "deferred_expense_account": null,
    "deferred_revenue_account": null,
    "expense_account": null,
    "income_account": null,
    "parent": "Sprayer",
    "parentfield": "item_group_defaults",
    "parenttype": "Item Group",
    "selling_cost_center": null
   }
  ],
  "item_group_name": "Sprayer",
  "modified": "2024-08-01 18:03:46.104995",
  "name": "Sprayer",
  "old_parent": "All Item Groups",
  "parent_item_group": "All Item Groups",
  "route": "sprayer",
  "show_in_website": 1,
  "slideshow": null,
  "taxes": [],
  "website_specifications": [],
  "website_title": null,
  "weightage": 0
 },
 {
  "description": null,
  "docstatus": 0,
  "doctype": "Item Group",
  "filter_attributes": [],
  "filter_fields": [],
  "image": null,
  "include_descendants": 0,
  "is_group": 1,
  "item_group_defaults": [],
  "item_group_name": "All Item Groups",
  "modified": "2024-07-26 11:08:28.236119",
  "name": "All Item Groups",
  "old_parent": "",
  "parent_item_group": "",
  "route": "all-item-groups",
  "show_in_website": 0,
  "slideshow": null,
  "taxes": [],
  "website_specifications": [],
  "website_title": null,
  "weightage": 0
 },
 {
  "description": null,
  "docstatus": 0,
  "doctype": "Item Group",
  "filter_attributes": [],
  "filter_fields": [],
  "image": "/files/manual sprayer.png",
  "include_descendants": 0,
  "is_group": 0,
  "item_group_defaults": [
   {
    "buying_cost_center": null,
    "company": "nature farmeasy",
    "default_discount_account": null,
    "default_price_list": "Standard Selling",
    "default_provisional_account": null,
    "default_supplier": null,
    "default_warehouse": "Stores - NF",
    "deferred_expense_account": null,
    "deferred_revenue_account": null,
    "expense_account": null,
    "income_account": null,
    "parent": "Seeder",
    "parentfield": "item_group_defaults",
    "parenttype": "Item Group",
    "selling_cost_center": null
   }
  ],
  "item_group_name": "Seeder",
  "modified": "2024-08-01 18:03:17.576247",
  "name": "Seeder",
  "old_parent": "All Item Groups",
  "parent_item_group": "All Item Groups",
  "route": "seeder",
  "show_in_website": 1,
  "slideshow": null,
  "taxes": [
   {
    "item_tax_template": "GST 5 % - NF",
    "maximum_net_rate": 0.0,
    "minimum_net_rate": 0.0,
    "parent": "Seeder",
    "parentfield": "taxes",
    "parenttype": "Item Group",
    "tax_category": null,
    "valid_from": null
   }
  ],
  "website_specifications": [],
  "website_title": null,
  "weightage": 0
 },
 {
  "description": null,
  "docstatus": 0,
  "doctype": "Item Group",
  "filter_attributes": [],
  "filter_fields": [],
  "image": "/files/solar mini traper.png",
  "include_descendants": 0,
  "is_group": 0,
  "item_group_defaults": [
   {
    "buying_cost_center": null,
    "company": "nature farmeasy",
    "default_discount_account": null,
    "default_price_list": "Standard Selling",
    "default_provisional_account": null,
    "default_supplier": null,
    "default_warehouse": "Stores - NF",
    "deferred_expense_account": null,
    "deferred_revenue_account": null,
    "expense_account": null,
    "income_account": null,
    "parent": "Charging Hubs",
    "parentfield": "item_group_defaults",
    "parenttype": "Item Group",
    "selling_cost_center": null
   }
  ],
  "item_group_name": "Charging Hubs",
  "modified": "2024-08-01 18:03:05.150725",
  "name": "Charging Hubs",
  "old_parent": "All Item Groups",
  "parent_item_group": "All Item Groups",
  "route": "charging-hubs",
  "show_in_website": 1,
  "slideshow": null,
  "taxes": [],
  "website_specifications": [],
  "website_title": null,
  "weightage": 0
 }
]